detect_attacks/__init__.py
detect_attacks/__main__.py
detect_attacks-0.0.12.dist-info/LICENSE
detect_attacks-0.0.12.dist-info/METADATA
detect_attacks-0.0.12.dist-info/WHEEL
detect_attacks-0.0.12.dist-info/top_level.txt
detect_attacks-0.0.12.dist-info/RECORD
