Metadata-Version: 2.1
Name: detect-attacks
Version: 0.0.12
Summary: A python package to detect attacks via networks
Home-page: UNKNOWN
Author: Van-Kha Nguyen
Author-email: hainguyen579@gmail.com
License: UNKNOWN
Platform: UNKNOWN
Classifier: Programming Language :: Python :: 2
Classifier: License :: OSI Approved :: MIT License
Classifier: Operating System :: OS Independent
